cloudshell_power_lib/Core.py
cloudshell_power_lib/Events.py
cloudshell_power_lib/Orchestration.py
cloudshell_power_lib/Resources.py
cloudshell_power_lib/ScreenLogger.py
cloudshell_power_lib/ShellDebugHelper.py
cloudshell_power_lib/__init__.py
src/Core.py
src/Events.py
src/Orchestration.py
src/Resources.py
src/ScreenLogger.py
src/ShellDebugHelper.py
src/__init__.py
cloudshell_power_lib-1.0.0.dist-info/LICENSE
cloudshell_power_lib-1.0.0.dist-info/METADATA
cloudshell_power_lib-1.0.0.dist-info/WHEEL
cloudshell_power_lib-1.0.0.dist-info/top_level.txt
cloudshell_power_lib-1.0.0.dist-info/RECORD
