Metadata-Version: 2.1
Name: cloudshell-power-lib
Version: 1.0.0
Summary: Quali Power Management support library
Home-page: https://github.com/QualiSystemsLab/Power-Management
Author: Quali Customer Success
Author-email: tim.s@quali.com
License: UNKNOWN
Platform: UNKNOWN
Classifier: Programming Language :: Python :: 2 :: Only
Classifier: License :: OSI Approved :: Apache Software License
Classifier: Operating System :: OS Independent
Requires-Dist: cloudshell-shell-core (<2.4.0,>=2.3.0)
Requires-Dist: cloudshell-orch-core (<2.1.0.0,>=2.0.0.0)
Requires-Dist: cloudshell-automation-api (<9.1.0.0,>=9.0.0.0)
